omneer/__init__.py
omneer/data/__init__.py
omneer/data/external/__init__.py
omneer/data/fusion/__init__.py
omneer/data/preprocessing/__init__.py
omneer/model/__init__.py
omneer/model/train.py
omneer/model/deeplearning/__init__.py
omneer/model/deeplearning/mlp.py
omneer/processing/__init__.py
omneer/processing/bootstrap.py
omneer/processing/main.py
omneer/processing/misc.py
omneer/visualization/__init__.py
omneer/visualization/plot.py
omneer/visualization/graph/__init__.py
omneer/visualization/graph/grid_search_.py
omneer/visualization/graph/plot_summary.py
omneer/visualization/graph/plot_swarm.py
omneer/visualization/graph/shap_1_aggregate.py
omneer/visualization/graph/shap_2_average.py
omneer/visualization/graph/shap_3_correlation.py
omneer/visualization/graph/shap_4_summary.py
omneer/visualization/graph/shap_analysis__.py
omneer_cli/__init__.py
omneer_cli/main.py
omneer-0.15.dist-info/METADATA
omneer-0.15.dist-info/WHEEL
omneer-0.15.dist-info/entry_points.txt
omneer-0.15.dist-info/top_level.txt
omneer-0.15.dist-info/RECORD
