Metadata-Version: 2.1
Name: omneer
Version: 0.15
Summary: Advanced personalized medicine diagnostics for neurodegenerative disorders
Home-page: http://docs.omneer.xyz
Author: William Blair
Author-email: william.blair0708@gmail.com
License: MIT
Platform: UNKNOWN
Classifier: Programming Language :: Python :: 3.8
Classifier: Programming Language :: Python :: 3.9
Classifier: Programming Language :: Python :: 3.10
Requires-Dist: numpy (>=1.19.0)
Requires-Dist: pandas (>=1.2.0)
Requires-Dist: matplotlib (>=3.3.0)
Requires-Dist: scipy (>=1.6.0)
Requires-Dist: requests (>=2.25.0)
Requires-Dist: beautifulsoup4 (>=4.9.0)
Requires-Dist: pytest (>=6.0.0)
Requires-Dist: flake8 (>=3.9.0)
Requires-Dist: black (>=21.6b0)
Requires-Dist: scikit-learn (>=0.24.0)
Requires-Dist: torch (>=1.9.0)
Requires-Dist: tqdm (>=4.62.0)
Requires-Dist: xgboost (>=1.4.0)
Requires-Dist: joblib (>=1.0.0)
Requires-Dist: click (>=8.0.1)
Requires-Dist: typer (>=0.3.2)
Requires-Dist: halo (>=0.0.31)
Requires-Dist: rich (>=10.6.0)
